dfa_gen/__init__.py
dfa_gen/dfa_class.py
dfa_gen/dfa_to_graph.py
dfa_gen/dfa_util.py
dfa_gen/generate_dfa.py
dfa_gen/generate_lattice.py
dfa_gen/data/coding_wheel.txt
dfa_gen/data/codon_freq_table.tsv
dfa_gen/data/codon_freq_table_alt.tsv
dfa_gen-1.2.0.dist-info/METADATA
dfa_gen-1.2.0.dist-info/WHEEL
dfa_gen-1.2.0.dist-info/entry_points.txt
dfa_gen-1.2.0.dist-info/top_level.txt
dfa_gen-1.2.0.dist-info/RECORD
