Metadata-Version: 2.1
Name: dfa-gen
Version: 1.2.0
Requires-Dist: pandas
Requires-Dist: graphviz
